nrsdk_dataset/__init__.py
nrsdk_dataset/dataset.py
nrsdk_dataset/slice_data.py
nrsdk_dataset/viz_dataset.py
nrsdk_dataset-1.681.dist-info/METADATA
nrsdk_dataset-1.681.dist-info/WHEEL
nrsdk_dataset-1.681.dist-info/top_level.txt
nrsdk_dataset-1.681.dist-info/RECORD
